kafka_mcp_server/__init__.py
kafka_mcp_server/kafka.py
kafka_mcp_server/main.py
kafka_mcp_server/server.py
kafka_mcp_server/settings.py
iflow_mcp_kafka_mcp_server-0.1.0.dist-info/METADATA
iflow_mcp_kafka_mcp_server-0.1.0.dist-info/WHEEL
iflow_mcp_kafka_mcp_server-0.1.0.dist-info/entry_points.txt
iflow_mcp_kafka_mcp_server-0.1.0.dist-info/licenses/LICENSE
iflow_mcp_kafka_mcp_server-0.1.0.dist-info/RECORD
