Metadata-Version: 2.4
Name: iflow-mcp_kafka_mcp_server
Version: 0.1.0
Summary: A Message Context Protocol (MCP) server that integrates with Apache Kafka
License-File: LICENSE
Requires-Python: >=3.8
Requires-Dist: aiokafka
Requires-Dist: confluent-kafka
Requires-Dist: mcp[cli]
Requires-Dist: pydantic-settings~=2.8.1
Requires-Dist: pydantic>=2.10.6
Requires-Dist: python-dotenv
